[{"name":"祝允明小楷东坡记游卷","text":"祝允明（1460—1526年），字希哲，号枝山，因手生六指，故自号枝指生，长洲（今江苏苏州）人。公元1492年（明弘治五年）举人，1514年（正德九年）授广东惠州府兴宁县知县，后转任南京应天府通判，故后世又称之为“祝京兆”。《明史》有传。工诗文书法，才华横溢，与唐寅、文徵明、徐祯卿并称“吴中四才子”。\n\n【名称】《东坡记游》卷 \n【作者】祝允明\n【书体】小楷\n【年代】明代\n【类别】书法\n【材质】纸本\n【收藏机构】辽宁省博物馆收藏 \n作品介绍\n祝允明楷书《东坡记游》卷，这卷小楷书录东坡“记”游若干节，为祝允明五十三岁时书写。其时，书家正值盛年，可谓其小楷书之代表作。款署“癸酉八月十二日步月宿东禅寺书此，枝山祝允明”。\n这件墨迹后有明代王宠、文彭、王世贞、张凤翼以及清代曹溶、罗坤、张陛等名家题跋．卷中钤有明、清收藏者印，以及乾隆、嘉庆、宣统内府鉴藏印。全卷纵十三点五厘米，横二百七十四厘米，现藏于辽宁省博物馆。 \n书法赏析\n此卷书法行笔稳健，结体严谨，通篇一气呵成，毫无懈怠。书法风格出自钟繇，用笔清健沉雄，不同的字，结构安排，富有变化，但长者不显其长，短者不觉其短，全卷千余字，虽是小楷，但通篇错落自然，神形具备，给人一种稳重、端庄的感觉。在禅院的虚空环境里书苏东坡的千古名篇，是产生这件心手双畅佳作的重要前提。 \n祝允明（1460—1526年），字希哲，号枝山，因手生六指，故自号枝指生，长洲（今江苏苏州）人。公元1492年（明弘治五年）举人，1514年（正德九年）授广东惠州府兴宁县知县，后转任南京应天府通判，故后世又称之为“祝京兆”。\n成就\n《明史》有传。工诗文书法，才华横溢，与唐寅、文徵明、徐祯卿并称“吴中四才子”。书工各体，融会贯通，蜚声于当时艺坛，与文徵明、王宠并称“吴中三家”，是明代中期极负盛名的书法家之一。其书法博采众长，远法晋唐，复具创新意趣，成为明代书家巨擘。楷书法钟、王宗虞、褚，行书学二王、苏轼，草法旭、素而兼取章草意韵，然法古人而不泥于古法，呈现出独特的书法风貌，自成一家 。枝山代表作是《太湖诗卷》、《箜篌引》、《赤壁赋》等。他为人豪爽，性格开朗，其无拘无束的气度，表现在“狂草”中，虽偶有失笔，却写得舒展纵逸，气韵生动，是值得后人研习的一位书家。 \n","category":"小楷","verified":true,"user":1,"timestamp":1429951616204},{"name":"祝允明小楷东坡记游卷","dynasty":"明代","category":"小楷","type":"","user":1,"timestamp":1429791643651,"text":"祝允明小楷《东坡记游卷》　\n  《东坡记游卷》为纸本，纵13.4厘米，横269.6厘米，款署“癸酉八月十二日步月宿东禅寺书此，枝山祝允明”。现藏辽宁省博物馆。","author":"明代祝允明","description":"祝允明小楷东坡记游卷"}]