[{"name":"董其昌跋赵令穰湖庄清夏图卷","text":"赵令穰（北宋）字大年，汴京（今河南开封市）人，生卒年不详，宋太祖赵匡胤五世孙。官至光州防御使﹑崇信军观察留后，卒赠“开府仪同三司”，追封“荣国公”。其子赵伯驹宋代著名画家，官至浙东兵马钤辖。工画山水、花果、翎毛，笔致秀 丽，尤长金碧山水。远师李思训父子。代表作品《风云期会图》、《春山图》、《阿阁图》、《后赤壁图 》、《文会图》、《鸟雀图》等。留传到现在的有《汉宫图》、《阿阁图》、《万松金阙图》等。\n宗室世系\n宋太祖赵匡胤---赵德芳--赵惟宪---赵从郁---赵世将---赵令穰\n人物生平\n赵令穰幼时即爱书画﹐富于文学修养﹐家藏有晋唐以来法书名画。他与画家文人时相往来。赵佶(宋徽宗)为端王时亦与他交游﹐切磋画艺。\n赵令穰的画多描绘湖边水滨水鸟凫雁飞集的景色﹐运思精妙﹐清丽雅致。雪景类王维﹐又学苏轼作小山丛竹﹐在士大夫中颇受称誉。黄庭坚题其所画芦雁云：“挥毫不作小池塘﹐芦荻江村落雁行﹐虽有珠帘巢翡翠﹐不忘烟雨罩鸳鸯。”又题其小景：“水色烟光上下寒﹐忘机鸥鸟恣飞还﹔年来频作江湖梦﹐对此身疑在故山。”其江村集雁﹑湖上飞鸥等意境荒远﹐富有诗意的小景山水﹐在宋代山水画中别具一格。\n因身处皇族之列﹐不能远游﹐所画题材多局限于两京(开封、洛阳)郊外景物，故每成一图，苏轼见之便嘲谓：“此必朝陵(朝拜皇陵)一番回矣！”现存《湖庄清夏图》描绘清幽的郊野景色﹐绿树板桥﹐凫鸟嬉水﹐湖庄临夏﹐意境颇为优美。\n弟令松字永年，神宗、哲宗两朝(1068-1100)官右武卫将军、隰州团练使，善画花竹、水墨蔬果，亦善山水。\n传世作品\n元符三年(1100)作《湖庄清夏图》卷，绢本，设色，款署：“元符庚辰大年笔”，现藏美国波士顿美术馆；《江村秋晓图》卷现藏美国纽约大都会博物馆；《橙黄橘绿图》册页，藏台北故宫博物院。\n","category":"草书","verified":true,"user":1,"timestamp":1429951648286}]