[{"name":"毛公鼎铭文","text":"百科名片\n毛公鼎铭文，专指西周晚期青铜器物毛公鼎之铭文，道光末年出土于陕西省宝鸡市岐山县。由作器人毛公（厂音）得名。直耳，半球腹，矮短的兽蹄形足，口沿饰环带状的重环纹。铭文32行499字，乃现存最长的铭文：完整的册命。共五段：其一，此时局势不宁；其二，宣王命毛公治理邦家内外；其三，给毛公予宣示王命之专权，着重申明未经毛公同意之命令，毛公可预示臣工不予奉行；其四，告诫勉励之词；其五，赏赐与对扬。是研究西周晚年政治史的重要史料。\n铭文内容\n王若曰：“父歆，丕显文武，皇天引厌劂德，配我有周，膺受大命，率怀不廷方亡不閈于文武耿光。唯天将集厥命，亦唯先正略又劂辟，属谨大命，肆皇天亡，临保我有周，丕巩先王配命，畏天疾威，司余小子弗，邦将曷吉？迹迹四方，大从丕静。呜呼！惧作小子溷湛于艰，永巩先王”。\n王曰：父歆，余唯?，至先王命，命汝?我邦，我家内外，?于小大政，?朕立，?许上下若否。宁四方死母童，祭一人才立，引唯乃智，余非庸又昏，汝母敢妄宁,虔夙夕，惠我一人，?我邦小大猷，毋折缄，告余先王若德，用印邵皇天，??大命，康能四国，俗我弗乍，先王?。\n王曰：父歆，余之庶出，入事于外，专命专政，?小大楚赋，无唯正闻，引其唯王智，?唯是丧我国，历自今，出入专命于外，厥非先告歆，父歆舍命，母又敢?专命于外。\n王曰：父歆，今余唯?先王命，命汝亟一方，弘我邦我家，母?于政，勿??庶口。母敢?事囊囊，??鳏寡，善效乃友正，母敢湛于酒，汝母敢?，才乃服，?夙夕，敬念王畏不赐。女母弗帅用先王乍明井，俗女弗以乃辟?于?。\n王曰：父歆，已曰及兹卿事寮，大史寮，于父即君，命女??公族?叁有司，小子，师氏，虎臣?朕亵事，以乃族干吾王身，取贵??，易女??一卣，?圭，?宝，朱市，?黄，玉?，金车，??载，朱?弘斩，虎?熏裹，右厄，画?，画?，金?，?卫，金?，金?，??，金??，鱼?，马四匹，攸?，金?，金?，朱?二?，易汝兹关，用?于政，毛公?对?天子皇休，用乍?鼎，子子孙孙永宝用。\n研究机构\n中国毛公鼎铭文研究会\n中国毛公鼎铭文研究会于2011年八月在安徽合肥成立。隶属中国神州书画艺术国际发展有限公司。主要研究以毛公鼎为代表的商周时期青铜铭文的艺术机构。中国毛公鼎铭文研究会由全国乃至港、澳、台地区毛公鼎研究专家、有识之士、锺鼎铭文爱好者、书法家自发组成的非盈利性的民间艺术团体。以中国神州书画院为依托，全面、系统的研究毛公鼎铭文，用书法表现出毛公鼎从铸造、铭字再到用笔、施墨方面的研究和探索。为广大锺鼎铭文爱好者、书法家领略远古文字信息，集字辍文提供理论依据。提高在大政、民风、修身、警句、格言、吉庆、祭祀等诸多方面的理解与借鉴。\n研究成果\n一、《毛公鼎铭文》，我国书法艺术有着悠久的历史和独特的风格，书家辈出，书法宝库十分丰富，《毛公鼎铭文》是为了适应广大初学者特别是中等学校学生临习传统书法的迫切要求，以及书法爱好者欣赏学习的需要而编辑了《毛公鼎铭文》。出版社:文物出版社;第1版(1999年1月1日)丛书名:历代碑贴法书选平装:34页正文语种:中文开本:16,16开ISBN:7501011354\n二、《刀笔八法》，由中国毛公鼎铭文研究会毛公鼎研究专家黄海德、刘克俊共同整理完成的以书法表现出毛公鼎从铸造、铭字再到用笔、施墨方面的研究和探索而总结出来的用笔方法。 \n","category":"草书","verified":true,"user":1,"timestamp":1429951663673}]