[{"name":"祝允明草书归去来辞","text":"简介\n名称：《归去来辞》扇面\n尺寸：纵19.0cm，横52.5cm\n时代：明\n广西壮族自治区博物馆馆藏文物。\n文化\n《归去来辞》扇面，王宠书，金笺，楷书。\n此扇录东晋著名诗人陶渊明的《归去来兮辞》，从“归去来兮！田园将芜胡不归！”到“乐天天命复奚疑！”款识：“雅宜子王宠书。”钤“王宠之印”白文印。此扇书法秀劲，笔墨精良，以己意书之，遒逸疏爽，具有其楷书中的典型风格。\n王宠（1494-1533年），字履吉，号雅宜山人，吴县（今江苏省苏州市）人。诗文书画皆精。书法初学蔡羽，后楷书师虞世南、智永，行书学王献之，融会贯通。小楷尤精，与祝允明、文徵明并称。\n","category":"草书","verified":true,"user":1,"timestamp":1429951617431},{"name":"祝允明草书归去来辞","dynasty":"明代","category":"草书","type":"","user":1,"timestamp":1429791643652,"text":"祝允明草书《归去来辞》，立轴，水墨纸本，98.5×24cm。正德五年（1510年）作。","author":"明代祝允明","description":"祝允明草书归去来辞"}]