[{"name":"王铎行书李贺诗帖","text":"王铎行书解析/名家名碑书法解析丛书是以清代书法这王铎著名书法名作《李贺诗册》为基础，从其字的书法艺术特点、笔法、结字、章法等四个方面进行分析讲解的。全书分为王铎的生平及其书法的形成影响、《李贺诗册帖》的笔法特征及其基本笔法解析和《李贺诗册帖》的结体风格、章法解析及款式示范三大部分，适合书法爱好者参考学习。\n第一章王铎的生平及其书法的形成影响\n第一节王铎的生平简历\n第二节王铎的书法形成及对后世的影响\n第三节王铎晚期行书名作及其艺术特色\n第四节怎样临习王铎行书\n第二章《李贺诗册帖》的笔法特征及其基本笔法解析\n……\n","category":"行书","verified":true,"user":1,"timestamp":1429951615529},{"name":"王铎行书李贺诗帖","dynasty":"明代","category":"行书","type":"","user":1,"timestamp":1429791623000,"text":"王铎《行书李贺诗帖》\n　　“观宋元明人书法，如赵子昂、文徵明，至于王铎、石涛，其字迹真伪易辨。真者用浓墨，下笔时必含水，含水乃润乃活。王铎之书，石涛之画，动落笔似墨沉，甚至笔未下而墨已滴纸上，此谓兴会淋漓，才与工匠描摹不同，有天趣，竟是在此。而不知者视为墨未调和，以为不工。非不能工，不屑工也”。\n　　上面这段话出自当代国画大师黄宾虹，我们以此观照王铎这通行书卷，真是最好的注脚。我们可以清楚地看出，王铎这卷行书卷，用墨是丰满的，但墨韵并不是一模一样，而是湿枯互见，变化丰富的。这个卷子落款为丁亥，是清顺治四年（1647）时书，王铎时年56岁。\n\n听颖师琴歌\n别浦云归桂花渚, 蜀国弦中双凤语.\n芙蓉叶落秋鸾离, 越王夜起游天姥.\n暗佩清臣敲水玉, 渡海蛾眉牵白鹿.\n谁看挟剑赴长桥, 谁看浸发题春竹.\n竺僧前立当吾门, 梵宫真相眉棱尊.\n古琴大轸长八尺, 峄阳老树非桐孙.\n凉馆闻弦惊病客, 药囊暂别龙须席.\n请歌直请卿相歌, 奉礼官卑复何益.\n\n昆仑使者\n昆仑使者无消息，茂陵烟树生愁色。\n金盘玉露自淋漓，元气茫茫收不得。\n麒麟背上石文裂，虬龙鳞下红枝折。\n何处偏伤万国心？中天夜久高明月。\n\n神仙曲\n碧峰海面藏灵书，上帝拣作神仙居。\n清明笑语闻空虚，斗乘巨浪骑鲸鱼。\n春罗书字邀王母，共宴红楼最深处。\n鹤羽冲风过海迟，不如却使青龙去。\n犹疑王母不相许，垂雾妖鬟更传语。\n\n高平县东私路\n侵侵槲叶香，木花滞寒雨。今夕山上秋，永谢无人处。\n石谿远荒涩，棠实悬辛苦。古者定幽寻，呼君作私路。\n丁亥六月 王铎","author":"明代王铎","description":"王铎行书李贺诗帖"}]