[{"name":"黄庭坚草书杜甫诗卷","text":"该帖系《宋元宝翰》册中的一开。笔法圆劲，笔势连绵，如龙蛇飞舞，达到心手两忘的境界。尾“寄贺兰铦”四字写作行楷书，矫拔精健，与前草书诗文的飞动气势相映生辉。虽短短八行，却是黄庭坚的草书佳作。此诗帖与藏于台北故宫博物院的黄庭坚《花气诗》帖堪称双美。\n作品原文\n朝野欢娱后，乾坤震荡中。\n相随万里日，总作白头翁。\n岁晚仍分袂，江边更转蓬。\n勿云俱异域，饮啄几回同。\n作品释文\n朝野欢娱后，乾坤震荡中。相随万里日，摠作白头翁。岁晚仍分袂，江边更转蓬。勿言居（此字点去）俱异域，饮啄几回同。寄贺兰铦。\n作品简介\n鉴藏印钤“内府书印”、“归来印”、“希之”。\n《吴氏书画记》卷五、《平生壮观》卷二、《石渠宝笈初编》卷二著录。\n黄庭坚(1045－1105)，字鲁直，自号山谷道人，晚号涪翁，又称黄豫章，洪州分宁（今江西修水）人。北宋诗人、词人、书法家，为盛极一时的江西诗派开山之祖。英宗治平四年(1067)进士。历官叶县尉、北京国子监教授、校书郎、著作佐郎、秘书丞、涪州别驾、黔州安置等。哲宗立，召为校书郎、《神宗实录》检讨官。后擢起居舍人。绍圣初，新党谓其修史“多诬”，贬涪州（今重庆涪陵）别驾，旋迁戎州（今四川宜宾），安置黔州等地。徽宗初，羁管宜州卒。宋英宗治平四年进士，绍圣初以校书郎坐修《神宗实录》失实被贬职，后来新党执政，屡遭贬，死于宜州（今广西宜山）贬所。 \n","category":"草书","verified":true,"user":1,"timestamp":1429951600904}]