[{"name":"欧阳询行书梦奠帖","text":"《梦奠帖》九行七十八字。横三十三点六厘米。结字劲险刻厉，森森然若武库之戈戟。纷披老笔，殆不可攀，有[欧行第一书也]之称，现藏辽宁省博物馆。\n\n出版日期：2005-12\n内容提要\n欧阳询（五五七——六四一）以欧体楷书领千年风骚，最具代表性的是《九成宫醴泉铭》碑，尽善尽美。他的行书、草书也是中规中矩，如《行书千字文》。也有[蝉联起伏、凝结遒耸，载萧（子云）永（智永）之柔懦，拉羲（之）献（之）之筋髓，此之诸势，出于自得，向背转折，深得二王风气]之作。\n此卷行书帖原为一集，一幅一事长卷，后被分拆，今仅存[梦奠、张翰、卜商]，合称[史事三帖]，高均为二十五点二厘米。\n","category":"行书","verified":true,"user":1,"timestamp":1429951554266},{"name":"欧阳询行书梦奠帖","dynasty":"唐代","category":"行书","type":"","user":1,"timestamp":1429791641402,"text":"【释文】仲尼梦奠，七十有二。周王九龄，具不满百。彭祖资以导养，樊重任性，裁过盈数，终归寂灭。无有得停住者。未有生而不老，老而不死。形归丘墓，神还所受，痛毒辛酸，何可熟念。善恶报应，如影随形，必不差二。\n全称《仲尼梦奠帖》，本帖无款印，纸本，25.5×33.6CM，七十八字，现藏于辽宁省博物馆。\n书法笔力苍劲古茂。曾入南宋内府收藏，钤有南宋“御府法书”朱文印记两方，“绍”“兴”朱文连珠印记，后经南宋贾似道，元郭天锡、乔篑成，明杨士奇、项元汴，清高士奇、清内府等递藏。\n此帖用墨淡而不浓，且是秃笔疾书，转折自如，无一笔不妥，无一笔凝滞，上下脉络映带清昕，结构稳重沉实，运笔从容，气韵流畅，体方而笔圆，妩媚而刚劲，为欧阳询晚年所书，清劲绝尘，诚属稀世之珍。","author":"唐代欧阳询","description":"欧阳询行书梦奠帖"}]