[{"name":"黄庭坚自书松风阁诗卷","text":"宋黄庭坚自书松风阁诗 是文物，现藏台北故宫博物院。1102年（崇宁元年）九月，黄庭坚与朋友游鄂城樊山，途经松林间一座亭阁，在此过夜，作了这首“松风阁”的诗，歌咏当时所看到的景物，并表达对朋友的怀念。这件书迹长波大撇，提顿起伏，一波三折，像是船夫摇桨用力的样子。不论收笔、转笔，都是楷书的笔法，下笔平和沉稳，变化非常含蓄，轻顿慢提，婀娜稳厚，意韵十足。在后段提到前一年已去世的苏轼时，心中不免激动，笔力特别凝重，结字也更加倾侧，是尚意书风的典型。\n\n【名称】宋黄庭坚自书松风阁诗\n【年代】宋代\n【文物原属】故宫旧藏\n【规格】诗卷，纸本，行书，纵：121.8厘米，横：129.1厘米。\n黄庭坚（1045～1105）字鲁直，号涪翁，江西分宁人。二十三岁中进士，历任汝州（河南）叶县县尉、北京国子监教授、秘书省校书郎等职。长于行书和草书，与蔡襄（1012～1067）、苏轼（1036～1101）、米芾（1051～1108）合称“宋四大家”。\n","category":"草书","verified":true,"user":1,"timestamp":1429951600343}]