[{"name":"陈绎曾静春先生诗集后序","text":"陈绎曾（生卒年月未详），元代元统、至正年间书法家。字伯敷，处州（今属浙江）人。举进士，官至国子监助教。\n\n【名称】元陈绎曾楷书静春先生诗集后序\n【规格】纸本，小楷，纵31.2厘米，横49.5厘米\n【现状】现藏故宫博物院。\n收藏跋印\n此序落款“至治元年三月既望”，即1321年。陈绎曾所书《静春先生诗集后序》是元人书《静春堂诗集》序卷中的一段。除陈绎曾，另有龚璛、陆文圭、杨载、汤弥昌等人作序，虞集、郭麟孙题跋，钱重鼎题诗以及黄溍撰写《故静春先生袁君墓志铭》。\n作品赏析\n此序以小楷书成，劲利有致，用笔精劲细腻，游刃有余，笔到之处清雅飘逸。按陶宗仪《书史会要》记载：“陈绎曾善于书法，真草篆隶俱通习之，各得其法。”陈绎曾的墨迹传世很少，此为其代表之作。\n静春堂为袁易所居斋堂的名称。《静春堂诗集》是袁易次子袁仲长裒辑其父遗稿编成，并请父亲的好友题序。陈绎曾所书《静春先生诗集后序》，是元人书《静春堂诗集》序卷中的一段。除陈绎曾外，另有龚璛、陆文圭、杨载、汤弥昌等人作序，虞集、郭麟孙题跋，钱重鼎题诗以及黄溍撰写《故静春先生袁君墓志铭》。从此序落款“至治元年三月既望”可推知，陈绎曾这件作品作于1321年。\n虽然有些口吃，但精敏异常，文辞汪洋浩博。诸经注疏，多能整段整段地背诵。元至正三年(1343)，任国史院编修，分撰《辽史》。著有《文筌谱论》、《古今文式》、《科举文阶》、《行文小谱》等。\n","category":"草书","verified":true,"user":1,"timestamp":1429951546805}]