[{"name":"吴昌硕行书题画诗","text":"此轴书法古拙遒劲，于法度之外别开生面。用笔时而厚重沉著，时而潇洒飘逸，起笔与横笔多沉实，撇笔多细长，有如其画梅之法。结字多欹侧，但以笔划之粗细保持字形的稳定，无倾倒之势，充分体现了吴氏书法“用笔遒劲，气息深厚”，“结体以上下左右取姿势”的书法特征，并可从中看到许多绘画的用笔特点，面貌独具一格。[1] \n\n名称：《行书诗》轴\n尺寸：纵130.2cm，横40.8cm。\n材料：纸本\n收藏：故宫博物院\n文物赏析\n《行书诗》轴，清，吴昌硕书，纸本，纵130.2cm，横40.8cm。\n释文：\n风香邻有无，花影佛跏趺。历劫龙吁盋，餐霞凤别梧。石真彊取（诗字点去）柱，诗奈不奇觚。山傥燕支夺，狂歌待老夫。普宁寺牡丹。丁卯凉秋录于癖斯堂。吴昌硕年八十四。本幅书录五言诗一首，末作者自识：“普宁寺牡丹丁卯凉秋录于癖斯堂，吴昌硕年八十四。”下钤“仓硕”印。无藏印。“丁卯”为1927年。普宁寺位于今杭州市余杭区仁和镇东塘普宁村，始建于五代后晋天福年间（936－944年），吴越王钱氏所建。普宁寺屡毁屡兴，明万历十六年（1588年）是最后一次重建。寺内原有“玉楼春”牡丹十八墩，相传为于谦手植，至清时花满庭院。今存六大本，花朵特大，白中带紫。据记载，普宁寺牡丹为塘栖二十四景之一，被誉为花中之魁。\n","category":"行书","verified":true,"user":1,"timestamp":1429951655032},{"name":"吴昌硕行书题画诗","dynasty":"清代","category":"行书","type":"","user":1,"timestamp":1429791615280,"text":"","author":"清代吴昌硕","description":"吴昌硕行书题画诗"}]