[{"name":"赵孟頫行书题二羊图","text":"图中画一羊低头吃草，一羊昂首瞻望，周围不着背景。右面的山羊张口睁目，尾巴上翘，身子向右而头部朝左，背部线条自然弯曲，羊毛轻软直长，描绘工细。左面的绵羊昂首而立，身躯朝左，头部右侧毛卷而短。全图纯用水墨画出，却显色斑斓之状。构图空疏，应是受到唐、宋家的影响。\n二羊图\n为元朝大书法家、画家所画\n纵25．2厘米，横48．4厘米\n现收藏于美国弗利尔美术馆\n此画为赵孟頫除马以外惟一绘有走兽的作品。画幅左侧自题：“余尝画马，未尝画羊。因仲信求画，余故戏为写生，虽不能逼近古人，颇于气韵有得。子昂。”钤“赵氏子昂”、“松雪斋”二印。画心上方又有乾隆皇帝于1784年御题，曰：“子昂常画马，仲信却求羊。三百群辞富，一双性具良。通灵无不妙，拔萃有谁方。跪乳畜中独，伊人寓意长。甲辰新正月，御题。”钤“古稀天子”、“犹日孜孜”二印。\n此画为赵孟頫除马以外惟一绘有走兽的作品。\n","category":"行书","verified":true,"user":1,"timestamp":1429951545324},{"name":"赵孟頫行书题二羊图","dynasty":"元代","category":"行书","type":"","user":1,"timestamp":1429791641718,"text":"赵孟頫题《二羊图》，行书。《二羊图》，赵孟頫绘，纸本水墨，纵25．2厘米，横48．4厘米。藏于美国弗利尔美术馆。\n释文：余尝画马，未尝画羊。因仲信求画，余故戏为写生，虽不能逼近古人，颇于气韵有得。子昂。","author":"元代赵孟頫","description":"赵孟頫行书题二羊图"}]